flaskeztest/__init__.py
flaskeztest/__main__.py
flaskeztest/exceptions.py
flaskeztest/eztest.py
flaskeztest/eztestcase.py
flaskeztest/eztestsuite.py
flaskeztest/helpers.py
flaskeztest-0.2.2.dist-info/METADATA
flaskeztest-0.2.2.dist-info/RECORD
flaskeztest-0.2.2.dist-info/WHEEL
flaskeztest-0.2.2.dist-info/entry_points.txt
flaskeztest-0.2.2.dist-info/top_level.txt
