Metadata-Version: 2.1
Name: flaskeztest
Version: 0.2.2
Summary: Tool to make integration testing flask app's using flask_sqlalchemy package easy to set up and organized
Home-page: https://github.com/Srokit/flask-eztest
Author: Stanley Rokita
Author-email: srok35@gmail.com
License: UNKNOWN
Platform: UNKNOWN
Requires-Dist: Flask
Requires-Dist: capybara-py
Requires-Dist: selenium
Requires-Dist: Flask-SQLAlchemy
Requires-Dist: termcolor
